{
    "prepare_queue": {
        "installed": [],
        "uninstalled": []
    },
    "config_munge": {
        "files": {}
    },
    "installed_plugins": {
        "cordova-plugin-whitelist": {
            "PACKAGE_NAME": "com.ionicframework.triviaionic664487"
        },
        "cordova-plugin-vibration": {
            "PACKAGE_NAME": "com.ionicframework.triviaionic664487"
        },
        "cordova-plugin-nativeaudio": {
            "PACKAGE_NAME": "com.ionicframework.triviaionic664487"
        },
        "cordova-plugin-splashscreen": {
            "PACKAGE_NAME": "com.ionicframework.triviaionic664487"
        }
    },
    "dependent_plugins": {}
}